small_ai/__init__.py
small_ai/core.py
small_ai/exceptions.py
small_ai/helpers.py
small_ai/io.py
small_ai-0.1.0a0.dist-info/LICENSE
small_ai-0.1.0a0.dist-info/METADATA
small_ai-0.1.0a0.dist-info/WHEEL
small_ai-0.1.0a0.dist-info/top_level.txt
small_ai-0.1.0a0.dist-info/RECORD
